[
    {
        "number": 1,
        "name": "Ashwini",
        "start_degree": 0.0,
        "end_degree": 13.3333,
        "lord": "Ketu",
        "deity": "Ashwini Kumaras (celestial physicians)",
        "symbol": "Horse's head",
        "shakti": "Power to quickly reach things/heal",
        "motivation": "Dharma",
        "guna": "Rajas",
        "gender": "Male",
        "animal": "Male Horse",
        "caste": "Vaishya (merchant)",
        "quality": "Swift, healing, adventurous",
        "description": "Ashwini natives are quick, energetic healers with pioneering spirit. They initiate new beginnings and have natural healing abilities. Fast-moving and impatient, they bring swift results."
    },
    {
        "number": 2,
        "name": "Bharani",
        "start_degree": 13.3333,
        "end_degree": 26.6667,
        "lord": "Venus",
        "deity": "Yama (god of death and dharma)",
        "symbol": "Yoni (female reproductive organ)",
        "shakti": "Power to take things away/cleanse",
        "motivation": "Artha",
        "guna": "Rajas",
        "gender": "Female",
        "animal": "Male Elephant",
        "caste": "Mleccha (outcaste)",
        "quality": "Restraining, transformative, intense",
        "description": "Bharani carries the energy of creation and destruction simultaneously. Natives are passionate, loyal, and carry heavy burdens with grace. They understand life-death cycles and possess tremendous creative power that must be channeled responsibly."
    },
    {
        "number": 3,
        "name": "Krittika",
        "start_degree": 26.6667,
        "end_degree": 40.0,
        "lord": "Sun",
        "deity": "Agni (god of fire)",
        "symbol": "Razor/flame/axe",
        "shakti": "Power to burn/purify",
        "motivation": "Kama",
        "guna": "Rajas",
        "gender": "Female",
        "animal": "Female Sheep",
        "caste": "Brahmin (priest)",
        "quality": "Sharp, purifying, critical",
        "description": "Krittika natives are sharp, critical, and purifying like fire itself. They cut through illusion with fierce determination and possess strong willpower. Their fiery nature makes them excellent leaders who demand truth and authenticity."
    },
    {
        "number": 4,
        "name": "Rohini",
        "start_degree": 40.0,
        "end_degree": 53.3333,
        "lord": "Moon",
        "deity": "Brahma (creator god)",
        "symbol": "Ox cart/chariot/temple",
        "shakti": "Power of growth/creation",
        "motivation": "Moksha",
        "guna": "Rajas",
        "gender": "Female",
        "animal": "Male Serpent",
        "caste": "Shudra (servant)",
        "quality": "Creative, fertile, beautiful",
        "description": "Rohini is the most fertile and creative nakshatra, beloved by the Moon. Natives are attractive, artistic, and materially abundant. They have magnetic charm and a deep appreciation for beauty, comfort, and sensual pleasures."
    },
    {
        "number": 5,
        "name": "Mrigashira",
        "start_degree": 53.3333,
        "end_degree": 66.6667,
        "lord": "Mars",
        "deity": "Soma (god of the Moon/nectar)",
        "symbol": "Deer's head",
        "shakti": "Power of fulfillment/searching",
        "motivation": "Dharma",
        "guna": "Rajas",
        "gender": "Male",
        "animal": "Female Serpent",
        "caste": "Vaishya (merchant)",
        "quality": "Searching, gentle, curious",
        "description": "Mrigashira natives are eternal seekers, always searching for the essence of things. They possess a gentle, curious nature like the deer, combined with Martian drive. Their restless quest for knowledge and experience makes them versatile and adaptable."
    },
    {
        "number": 6,
        "name": "Ardra",
        "start_degree": 66.6667,
        "end_degree": 80.0,
        "lord": "Rahu",
        "deity": "Rudra (god of storms/destruction)",
        "symbol": "Teardrop/diamond/human head",
        "shakti": "Power of effort/achieving goals through struggle",
        "motivation": "Artha",
        "guna": "Rajas",
        "gender": "Female",
        "animal": "Female Dog",
        "caste": "Mleccha (outcaste)",
        "quality": "Stormy, transformative, intellectual",
        "description": "Ardra brings the storm of transformation that clears away the old. Natives experience intense emotional upheavals that lead to profound growth. They possess sharp intellect, research ability, and the courage to destroy what no longer serves."
    },
    {
        "number": 7,
        "name": "Punarvasu",
        "start_degree": 80.0,
        "end_degree": 93.3333,
        "lord": "Jupiter",
        "deity": "Aditi (mother of the gods)",
        "symbol": "Bow and quiver of arrows/house",
        "shakti": "Power of renewal/returning to source",
        "motivation": "Kama",
        "guna": "Rajas",
        "gender": "Male",
        "animal": "Female Cat",
        "caste": "Vaishya (merchant)",
        "quality": "Renewing, optimistic, wise",
        "description": "Punarvasu embodies the energy of renewal and return. Natives bounce back from adversity with remarkable resilience and optimism. They are philosophical, nurturing, and possess an innate wisdom that helps them find their way home no matter how far they wander."
    },
    {
        "number": 8,
        "name": "Pushya",
        "start_degree": 93.3333,
        "end_degree": 106.6667,
        "lord": "Saturn",
        "deity": "Brihaspati (Jupiter, priest of the gods)",
        "symbol": "Cow's udder/lotus/arrow/circle",
        "shakti": "Power to create spiritual energy/nourishment",
        "motivation": "Moksha",
        "guna": "Rajas",
        "gender": "Male",
        "animal": "Male Sheep",
        "caste": "Kshatriya (warrior)",
        "quality": "Nourishing, spiritual, auspicious",
        "description": "Pushya is considered the most auspicious nakshatra for spiritual growth and nourishment. Natives are generous, devoted, and selflessly caring. They possess deep faith, strong ethics, and the ability to nourish others through their wisdom and resources."
    },
    {
        "number": 9,
        "name": "Ashlesha",
        "start_degree": 106.6667,
        "end_degree": 120.0,
        "lord": "Mercury",
        "deity": "Naga (serpent gods)",
        "symbol": "Coiled serpent",
        "shakti": "Power to inflict poison/hypnotize",
        "motivation": "Dharma",
        "guna": "Rajas",
        "gender": "Female",
        "animal": "Male Cat",
        "caste": "Mleccha (outcaste)",
        "quality": "Mystical, cunning, penetrating",
        "description": "Ashlesha carries the potent, hypnotic energy of the serpent. Natives are deeply intuitive, psychologically penetrating, and possess hidden power. They can be manipulative or healing depending on their evolution, wielding the kundalini force with intensity."
    },
    {
        "number": 10,
        "name": "Magha",
        "start_degree": 120.0,
        "end_degree": 133.3333,
        "lord": "Ketu",
        "deity": "Pitris (ancestral fathers)",
        "symbol": "Royal throne/palanquin",
        "shakti": "Power to leave the body/ancestral connection",
        "motivation": "Artha",
        "guna": "Tamas",
        "gender": "Female",
        "animal": "Male Rat",
        "caste": "Shudra (servant)",
        "quality": "Royal, ancestral, authoritative",
        "description": "Magha bestows regal authority and deep connection to ancestral lineage. Natives carry themselves with dignity, command respect, and honor tradition. They have natural leadership qualities and a strong sense of heritage and duty to their family line."
    },
    {
        "number": 11,
        "name": "Purva Phalguni",
        "start_degree": 133.3333,
        "end_degree": 146.6667,
        "lord": "Venus",
        "deity": "Bhaga (god of delight and marital bliss)",
        "symbol": "Front legs of a bed/hammock/fig tree",
        "shakti": "Power of creative procreation",
        "motivation": "Kama",
        "guna": "Tamas",
        "gender": "Female",
        "animal": "Female Rat",
        "caste": "Brahmin (priest)",
        "quality": "Creative, romantic, luxurious",
        "description": "Purva Phalguni radiates warmth, creativity, and the joy of living. Natives are artistic, romantic, and drawn to pleasure and beauty. They possess natural charisma, enjoy socializing, and have a talent for bringing happiness and celebration to others."
    },
    {
        "number": 12,
        "name": "Uttara Phalguni",
        "start_degree": 146.6667,
        "end_degree": 160.0,
        "lord": "Sun",
        "deity": "Aryaman (god of patronage and kindness)",
        "symbol": "Back legs of a bed/fig tree",
        "shakti": "Power of giving prosperity through union",
        "motivation": "Moksha",
        "guna": "Tamas",
        "gender": "Female",
        "animal": "Male Cow",
        "caste": "Kshatriya (warrior)",
        "quality": "Helpful, generous, contractual",
        "description": "Uttara Phalguni represents the energy of partnership, patronage, and social contracts. Natives are generous, responsible, and skilled at building lasting alliances. They bring people together and excel in roles requiring fairness, leadership, and benevolent authority."
    },
    {
        "number": 13,
        "name": "Hasta",
        "start_degree": 160.0,
        "end_degree": 173.3333,
        "lord": "Moon",
        "deity": "Savitar (creative aspect of the Sun god)",
        "symbol": "Open hand/palm/fist",
        "shakti": "Power to manifest what one seeks/gain mastery",
        "motivation": "Dharma",
        "guna": "Tamas",
        "gender": "Male",
        "animal": "Female Buffalo",
        "caste": "Vaishya (merchant)",
        "quality": "Skillful, clever, industrious",
        "description": "Hasta natives are extraordinarily dexterous and resourceful, with skilled hands and sharp minds. They excel in craftsmanship, healing arts, and any work requiring precision. Their wit and cleverness make them adaptable problem-solvers who manifest goals through effort."
    },
    {
        "number": 14,
        "name": "Chitra",
        "start_degree": 173.3333,
        "end_degree": 186.6667,
        "lord": "Mars",
        "deity": "Tvashtar (celestial architect/craftsman)",
        "symbol": "Shining jewel/pearl",
        "shakti": "Power to accumulate merit/create beauty",
        "motivation": "Artha",
        "guna": "Tamas",
        "gender": "Female",
        "animal": "Female Tiger",
        "caste": "Mleccha (outcaste)",
        "quality": "Brilliant, artistic, visionary",
        "description": "Chitra shines like a brilliant jewel, bestowing beauty, creativity, and architectural vision. Natives possess an eye for aesthetics and design, creating things of lasting beauty. They are charismatic, dynamic, and drawn to transform raw materials into works of art."
    },
    {
        "number": 15,
        "name": "Swati",
        "start_degree": 186.6667,
        "end_degree": 200.0,
        "lord": "Rahu",
        "deity": "Vayu (god of wind)",
        "symbol": "Young sprout blown by wind/coral",
        "shakti": "Power to scatter like the wind",
        "motivation": "Kama",
        "guna": "Tamas",
        "gender": "Female",
        "animal": "Male Buffalo",
        "caste": "Mleccha (outcaste)",
        "quality": "Independent, flexible, diplomatic",
        "description": "Swati embodies the free-spirited energy of the wind, bending without breaking. Natives are independent, diplomatic, and skilled in commerce and communication. They adapt to any environment while maintaining inner freedom and possess a talent for business and negotiation."
    },
    {
        "number": 16,
        "name": "Vishakha",
        "start_degree": 200.0,
        "end_degree": 213.3333,
        "lord": "Jupiter",
        "deity": "Indra-Agni (king of gods and fire god combined)",
        "symbol": "Triumphal archway/potter's wheel",
        "shakti": "Power to achieve many fruits/single-pointed focus",
        "motivation": "Moksha",
        "guna": "Tamas",
        "gender": "Female",
        "animal": "Male Tiger",
        "caste": "Mleccha (outcaste)",
        "quality": "Determined, focused, ambitious",
        "description": "Vishakha natives possess incredible determination and single-pointed focus toward their goals. They are ambitious, purposeful, and willing to endure hardship to achieve success. Their forked nature gives them versatility, but their greatest power lies in unwavering commitment to a chosen path."
    },
    {
        "number": 17,
        "name": "Anuradha",
        "start_degree": 213.3333,
        "end_degree": 226.6667,
        "lord": "Saturn",
        "deity": "Mitra (god of friendship and devotion)",
        "symbol": "Lotus flower/triumphal archway",
        "shakti": "Power of worship/devotion",
        "motivation": "Dharma",
        "guna": "Tamas",
        "gender": "Male",
        "animal": "Female Deer",
        "caste": "Shudra (servant)",
        "quality": "Devoted, friendly, organized",
        "description": "Anuradha combines Saturnine discipline with the warmth of divine friendship. Natives excel at building organizations, maintaining devotion, and forming deep bonds. Like the lotus rising from mud, they bloom beautifully even in harsh conditions and inspire others through their loyalty."
    },
    {
        "number": 18,
        "name": "Jyeshtha",
        "start_degree": 226.6667,
        "end_degree": 240.0,
        "lord": "Mercury",
        "deity": "Indra (king of the gods)",
        "symbol": "Circular amulet/earring/umbrella",
        "shakti": "Power to rise and conquer/gain courage in battle",
        "motivation": "Artha",
        "guna": "Tamas",
        "gender": "Female",
        "animal": "Male Deer",
        "caste": "Vaishya (merchant)",
        "quality": "Protective, senior, powerful",
        "description": "Jyeshtha carries the energy of the elder, the protector, and the chief. Natives possess natural authority, sharp intelligence, and protective instincts. They rise to positions of seniority through merit and courage, though they must guard against arrogance and jealousy."
    },
    {
        "number": 19,
        "name": "Mula",
        "start_degree": 240.0,
        "end_degree": 253.3333,
        "lord": "Ketu",
        "deity": "Nirriti (goddess of destruction/calamity)",
        "symbol": "Tied bunch of roots/elephant goad",
        "shakti": "Power to destroy/break things apart",
        "motivation": "Kama",
        "guna": "Sattva",
        "gender": "Male",
        "animal": "Male Dog",
        "caste": "Mleccha (outcaste)",
        "quality": "Investigative, destructive, foundational",
        "description": "Mula digs to the very root of existence, destroying superficiality to find truth. Natives are philosophical investigators who question everything and tear down false structures. Their destructive power serves a higher purpose of getting to the foundation of knowledge and reality."
    },
    {
        "number": 20,
        "name": "Purva Ashadha",
        "start_degree": 253.3333,
        "end_degree": 266.6667,
        "lord": "Venus",
        "deity": "Apas (goddess of water/cosmic waters)",
        "symbol": "Elephant tusk/fan/winnowing basket",
        "shakti": "Power of invigoration/declaration of war",
        "motivation": "Moksha",
        "guna": "Sattva",
        "gender": "Female",
        "animal": "Male Monkey",
        "caste": "Brahmin (priest)",
        "quality": "Invincible, purifying, proud",
        "description": "Purva Ashadha carries the invincible energy of cosmic waters that purify and rejuvenate everything they touch. Natives possess unshakeable conviction and the ability to inspire others with their vision. They declare their truth boldly and have a talent for philosophical debate and persuasion."
    },
    {
        "number": 21,
        "name": "Uttara Ashadha",
        "start_degree": 266.6667,
        "end_degree": 280.0,
        "lord": "Sun",
        "deity": "Vishvadevas (universal gods/ten Vishvadevas)",
        "symbol": "Elephant tusk/small cot/planks of bed",
        "shakti": "Power of unchallengeable victory",
        "motivation": "Dharma",
        "guna": "Sattva",
        "gender": "Female",
        "animal": "Female Mongoose",
        "caste": "Kshatriya (warrior)",
        "quality": "Victorious, righteous, enduring",
        "description": "Uttara Ashadha bestows final, lasting victory through righteous action and universal principles. Natives possess unwavering integrity, leadership ability, and the patience to achieve enduring success. They are the ultimate victors who succeed through dharma rather than force."
    },
    {
        "number": 22,
        "name": "Shravana",
        "start_degree": 280.0,
        "end_degree": 293.3333,
        "lord": "Moon",
        "deity": "Vishnu (the preserver)",
        "symbol": "Three footprints/ear/trident",
        "shakti": "Power of connection/listening",
        "motivation": "Artha",
        "guna": "Sattva",
        "gender": "Male",
        "animal": "Female Monkey",
        "caste": "Mleccha (outcaste)",
        "quality": "Learned, perceptive, connecting",
        "description": "Shravana is the nakshatra of deep listening and the transmission of knowledge. Natives are excellent learners, counselors, and communicators who absorb wisdom through attentive hearing. They connect people and ideas, serving as bridges between different worlds and traditions."
    },
    {
        "number": 23,
        "name": "Dhanishta",
        "start_degree": 293.3333,
        "end_degree": 306.6667,
        "lord": "Mars",
        "deity": "Vasus (eight elemental gods of nature)",
        "symbol": "Drum/flute/mridanga",
        "shakti": "Power to give abundance and fame",
        "motivation": "Kama",
        "guna": "Sattva",
        "gender": "Female",
        "animal": "Female Lion",
        "caste": "Vaishya (merchant)",
        "quality": "Musical, wealthy, rhythmic",
        "description": "Dhanishta resonates with the rhythm of abundance, music, and material prosperity. Natives are talented in music and dance, generous with their wealth, and attuned to cosmic rhythms. They possess natural timing and the ability to create harmony in all areas of life."
    },
    {
        "number": 24,
        "name": "Shatabhisha",
        "start_degree": 306.6667,
        "end_degree": 320.0,
        "lord": "Rahu",
        "deity": "Varuna (god of cosmic waters and law)",
        "symbol": "Empty circle/hundred flowers or physicians",
        "shakti": "Power of healing/covering wide space",
        "motivation": "Moksha",
        "guna": "Sattva",
        "gender": "Male",
        "animal": "Female Horse",
        "caste": "Mleccha (outcaste)",
        "quality": "Healing, secretive, philosophical",
        "description": "Shatabhisha is the nakshatra of a hundred healers, governed by Varuna's cosmic laws. Natives are reclusive, deeply philosophical, and possess remarkable healing abilities. They guard ancient secrets, work with unconventional medicine, and seek truth beyond the veil of illusion."
    },
    {
        "number": 25,
        "name": "Purva Bhadrapada",
        "start_degree": 320.0,
        "end_degree": 333.3333,
        "lord": "Jupiter",
        "deity": "Aja Ekapada (one-footed goat/cosmic fire serpent)",
        "symbol": "Front of funeral cot/two-faced man/sword",
        "shakti": "Power to raise evolutionary level/spiritual fire",
        "motivation": "Dharma",
        "guna": "Sattva",
        "gender": "Male",
        "animal": "Male Lion",
        "caste": "Brahmin (priest)",
        "quality": "Fiery, transformative, ascetic",
        "description": "Purva Bhadrapada channels the fierce fire of spiritual transformation and penance. Natives oscillate between worldly passion and ascetic renunciation. They possess tremendous spiritual intensity, can be radical or extreme, and serve as agents of profound change in the world."
    },
    {
        "number": 26,
        "name": "Uttara Bhadrapada",
        "start_degree": 333.3333,
        "end_degree": 346.6667,
        "lord": "Saturn",
        "deity": "Ahir Budhnya (serpent of the deep/dragon of the depths)",
        "symbol": "Back legs of funeral cot/twin/serpent in water",
        "shakti": "Power of bringing rain/cosmic stability",
        "motivation": "Artha",
        "guna": "Sattva",
        "gender": "Male",
        "animal": "Female Cow",
        "caste": "Kshatriya (warrior)",
        "quality": "Deep, stable, compassionate",
        "description": "Uttara Bhadrapada represents the depths of cosmic wisdom and controlled spiritual power. Natives are deeply compassionate, emotionally stable, and possess profound inner strength. They embody the calm after the storm, offering shelter, wisdom, and genuine selfless service to others."
    },
    {
        "number": 27,
        "name": "Revati",
        "start_degree": 346.6667,
        "end_degree": 360.0,
        "lord": "Mercury",
        "deity": "Pushan (nourisher god/protector of travelers)",
        "symbol": "Fish/pair of fish/drum",
        "shakti": "Power of nourishment/safe journey",
        "motivation": "Kama",
        "guna": "Sattva",
        "gender": "Female",
        "animal": "Female Elephant",
        "caste": "Shudra (servant)",
        "quality": "Nourishing, protective, transcendent",
        "description": "Revati is the final nakshatra, representing the completion of the soul's journey and safe passage to the next realm. Natives are gentle, caring, and deeply empathetic with a talent for nurturing others. They possess an otherworldly quality and serve as guides for those navigating life's transitions."
    }
]
